echoviz/__init__.py
echoviz/threed/__init__.py
echoviz/threed/animated.py
echoviz/threed/distance.py
echoviz/threed/interactive.py
echoviz/threed/static.py
echoviz/twod/__init__.py
echoviz/twod/animated.py
echoviz/twod/slicing.py
echoviz/utils/__init__.py
echoviz/utils/colors.py
echoviz/utils/layouts.py
echoviz/utils/misc.py
echoviz/utils/voxel_grid.py
echoviz_MALOU-0.2.3.dist-info/LICENSE
echoviz_MALOU-0.2.3.dist-info/METADATA
echoviz_MALOU-0.2.3.dist-info/WHEEL
echoviz_MALOU-0.2.3.dist-info/top_level.txt
echoviz_MALOU-0.2.3.dist-info/RECORD
