Metadata-Version: 2.1
Name: echoviz-MALOU
Version: 0.2.3
Summary: Visualisation of 3D mitral valve
Home-page: https://github.com/mailys-hau/echoviz
Author: Maïlys HAU
Author-email: Maïlys Hau <27966914+mailys-hau@users.noreply.github.com>
Project-URL: Homepage, https://github.com/mailys-hau/echoviz
Project-URL: Bug Tracker, https://github.com/mailys-hau/echoviz/issues
Keywords: visualisation,plotly,3D,mitral valve
Classifier: Development Status :: 4 - Beta
Classifier: Framework :: Dash
Classifier: Framework :: IPython
Classifier: Framework :: Jupyter :: JupyterLab
Classifier: Intended Audience :: Developers
Classifier: Intended Audience :: Science/Research
Classifier: License :: OSI Approved :: GNU General Public License v3 (GPLv3)
Classifier: Operating System :: Unix
Classifier: Programming Language :: Python :: 3
Classifier: Topic :: Scientific/Engineering :: Visualization
Requires-Python: >=3.7
License-File: LICENSE
Requires-Dist: kaleido
Requires-Dist: numpy
Requires-Dist: pandas
Requires-Dist: pillow
Requires-Dist: plotly
Requires-Dist: pysdf
Requires-Dist: scikit-image
Requires-Dist: ipython
